genshin_mummy/__init__.py
genshin_mummy/opt.py
genshin_mummy/type.py
genshin_mummy/artifact_helper/__init__.py
genshin_mummy/artifact_helper/exception.py
genshin_mummy/artifact_helper/judge.py
genshin_mummy/artifact_helper/page_manager.py
genshin_mummy/artifact_helper/type.py
genshin_mummy/artifact_helper/unlock_shit_artifact.py
genshin_mummy/materials/inventory/artifact_icon.jpg
genshin_mummy/materials/inventory/development_items_icon.jpg
genshin_mummy/materials/inventory/filter_icon.jpg
genshin_mummy/materials/inventory/locked_icon.jpg
genshin_mummy/materials/inventory/unlocked_icon.jpg
genshin_mummy/materials/inventory/weapon_icon.jpg
genshin_mummy/materials/inventory/weapon_icon.pkl
genshin_mummy/materials/menu_page/exit_icon.jpg
genshin_mummy/materials/menu_page/inventory_icon.jpg
genshin_mummy/ocr/__init__.py
genshin_mummy/ocr/opt.py
genshin_mummy/ocr/type.py
genshin_mummy/tools/__init__.py
genshin_mummy/tools/locator.py
genshin_mummy/tools/logger.py
genshin_mummy/tools/selector.py
genshin_mummy-1.0.1.dist-info/entry_points.txt
genshin_mummy-1.0.1.dist-info/LICENSE
genshin_mummy-1.0.1.dist-info/WHEEL
genshin_mummy-1.0.1.dist-info/METADATA
genshin_mummy-1.0.1.dist-info/RECORD
