Metadata-Version: 2.1
Name: genshin-mummy
Version: 1.0.1
Summary: A tech-neet's RPA project for Genshin Impact.
Author-email: LetianLiu <15261172997@163.com>
Classifier: License :: OSI Approved :: MIT License
Requires-Dist: attrs~=23.1.0
Requires-Dist: iolite~=22.2.0
Requires-Dist: numpy~=1.24.4
Requires-Dist: openpyxl~=3.1.2
Requires-Dist: pyautogui~=0.9.54
Requires-Dist: pillow~=10.1.0
Requires-Dist: pyscreeze~=0.1.30
Requires-Dist: opencv-python~=4.6.0.66
Requires-Dist: paddlepaddle~=2.5.2
Requires-Dist: paddleocr~=2.7.0.3
Requires-Dist: termcolor~=2.3.0
Requires-Dist: yapf~=0.40.2 ; extra == "dev"
Requires-Dist: pytest~=7.4.3 ; extra == "dev"
Project-URL: Homepage, https://github.com/Tpinion/GenshinMummy
Project-URL: Issues, https://github.com/Tpinion/GenshinMummy/issues
Provides-Extra: dev
